langchain_ai21/__init__.py
langchain_ai21/ai21_base.py
langchain_ai21/chat/__init__.py
langchain_ai21/chat/chat_adapter.py
langchain_ai21/chat/chat_factory.py
langchain_ai21/chat/chat_maestro.py
langchain_ai21/chat_models.py
langchain_ai21/examples/__init__.py
langchain_ai21/examples/prompt_generation_ai21_maestro.py
langchain_ai21/py.typed
langchain_ai21-1.2.0.dist-info/LICENSE
langchain_ai21-1.2.0.dist-info/METADATA
langchain_ai21-1.2.0.dist-info/WHEEL
langchain_ai21-1.2.0.dist-info/RECORD
