Metadata-Version: 2.1
Name: langchain-ai21
Version: 1.2.0
Summary: An integration package connecting AI21 and LangChain
Home-page: https://github.com/langchain-ai/langchain-ai21
License: MIT
Requires-Python: >=3.9,<4.0
Classifier: License :: OSI Approved :: MIT License
Classifier: Programming Language :: Python :: 3
Classifier: Programming Language :: Python :: 3.9
Classifier: Programming Language :: Python :: 3.10
Classifier: Programming Language :: Python :: 3.11
Classifier: Programming Language :: Python :: 3.12
Requires-Dist: ai21 (>=3.3.0,<4.0.0)
Requires-Dist: langchain-core (>=0.3,<0.4)
Project-URL: Repository, https://github.com/langchain-ai/langchain-ai21
Project-URL: Release Notes, https://github.com/langchain-ai/langchain-ai21/releases
Project-URL: Source Code, https://github.com/langchain-ai/langchain-ai21/tree/main/libs/ai21
